{"540": {"price": "2970"}, "541": {"price": "2970"}, "542": {"price": "2970"}, "543": {"price": "2970"}, "544": {"price": "2970"}, "545": {"price": "2970"}, "546": {"price": "2970"}, "547": {"price": "2970"}, "548": {"price": "2970"}, "549": {"price": "2970"}, "550": {"price": "2970"}, "551": {"price": "2970"}, "552": {"price": "2970"}, "553": {"price": "2970"}, "554": {"price": "2970"}, "555": {"price": "2970"}, "556": {"price": "2970"}, "557": {"price": "2970"}, "558": {"price": "2970"}, "559": {"price": "2970"}, "560": {"price": "2970"}, "561": {"price": "2970"}, "562": {"price": "2970"}, "563": {"price": "2970"}, "564": {"price": "2970"}, "565": {"price": "2970"}, "566": {"price": "2970"}, "567": {"price": "2970"}, "568": {"price": "2970"}, "569": {"price": "2970"}, "570": {"price": "2970"}, "571": {"price": "2970"}, "572": {"price": "2970"}, "573": {"price": "2970"}, "574": {"price": "2970"}, "575": {"price": "2970"}, "576": {"price": "2970"}, "577": {"price": "2970"}, "578": {"price": "2970"}, "579": {"price": "2970"}, "580": {"price": "2970"}, "581": {"price": "2970"}, "582": {"price": "2970"}, "583": {"price": "2970"}, "584": {"price": "2970"}, "585": {"price": "2970"}, "586": {"price": "2970"}, "587": {"price": "2970"}, "588": {"price": "2970"}, "589": {"price": "2970"}, "590": {"price": "2970"}, "591": {"price": "2970"}, "592": {"price": "2970"}, "593": {"price": "2970"}, "594": {"price": "2970"}, "595": {"price": "2970"}, "596": {"price": "2970"}, "597": {"price": "2970"}, "598": {"price": "2970"}, "599": {"price": "2970"}, "600": {"price": "297357"}, "601": {"price": "296070"}, "602": {"price": "296961"}, "603": {"price": "297060"}, "604": {"price": "297060"}, "605": {"price": "296961"}, "606": {"price": "296367"}, "607": {"price": "296367"}, "608": {"price": "296070"}, "609": {"price": "296070"}, "610": {"price": "296367"}, "611": {"price": "296169"}, "612": {"price": "296961"}, "613": {"price": "296961"}, "614": {"price": "297258"}, "615": {"price": "299040"}, "616": {"price": "299040"}, "617": {"price": "298941"}, "618": {"price": "299040"}, "619": {"price": "298941"}, "620": {"price": "297753"}, "621": {"price": "297258"}, "622": {"price": "296961"}, "623": {"price": "296961"}, "624": {"price": "296169"}, "625": {"price": "295674"}, "626": {"price": "295575"}, "627": {"price": "295278"}, "628": {"price": "295179"}, "629": {"price": "295080"}, "630": {"price": "295674"}, "631": {"price": "295179"}, "632": {"price": "295575"}, "633": {"price": "295674"}, "634": {"price": "295575"}, "635": {"price": "296565"}, "636": {"price": "295575"}, "637": {"price": "295773"}, "638": {"price": "295674"}, "639": {"price": "295080"}, "640": {"price": "294981"}, "641": {"price": "294585"}, "642": {"price": "294486"}, "643": {"price": "293694"}, "644": {"price": "2925105"}, "645": {"price": "2924106"}, "646": {"price": "293298"}, "647": {"price": "293199"}, "648": {"price": "2930100"}, "649": {"price": "293199"}, "650": {"price": "298545"}, "651": {"price": "296763"}, "652": {"price": "296070"}, "653": {"price": "295476"}, "654": {"price": "295476"}, "655": {"price": "295278"}, "656": {"price": "294981"}, "657": {"price": "294981"}, "658": {"price": "294981"}, "659": {"price": "294783"}, "660": {"price": "294585"}, "661": {"price": "294189"}, "662": {"price": "294288"}, "663": {"price": "298743"}, "664": {"price": "298149"}, "665": {"price": "298050"}, "666": {"price": "296961"}, "667": {"price": "296565"}, "668": {"price": "298149"}, "669": {"price": "297555"}, "670": {"price": "298050"}, "671": {"price": "298050"}, "672": {"price": "297357"}, "673": {"price": "297357"}, "674": {"price": "297456"}, "675": {"price": "296961"}, "676": {"price": "296664"}, "677": {"price": "297258"}, "678": {"price": "297060"}, "679": {"price": "297060"}, "680": {"price": "296763"}, "681": {"price": "296763"}, "682": {"price": "297060"}, "683": {"price": "297357"}, "684": {"price": "296763"}, "685": {"price": "296664"}, "686": {"price": "296565"}, "687": {"price": "296466"}, "688": {"price": "296466"}, "689": {"price": "296466"}, "690": {"price": "296466"}, "691": {"price": "296565"}, "692": {"price": "296466"}, "693": {"price": "296169"}, "694": {"price": "296169"}, "695": {"price": "296070"}, "696": {"price": "296169"}, "697": {"price": "296169"}, "698": {"price": "296070"}, "699": {"price": "296070"}, "700": {"price": "295971"}, "701": {"price": "295278"}, "702": {"price": "295179"}, "703": {"price": "294981"}, "704": {"price": "294981"}, "705": {"price": "294882"}, "706": {"price": "294783"}, "707": {"price": "294783"}, "708": {"price": "294783"}, "709": {"price": "294585"}, "710": {"price": "294684"}, "711": {"price": "294882"}, "712": {"price": "294684"}, "713": {"price": "294288"}, "714": {"price": "294486"}, "715": {"price": "294882"}, "716": {"price": "293991"}, "717": {"price": "293595"}, "718": {"price": "293793"}, "719": {"price": "293694"}, "720": {"price": "2930100"}, "721": {"price": "2930100"}, "722": {"price": "2930100"}, "723": {"price": "2929101"}, "724": {"price": "2930100"}, "725": {"price": "2929101"}, "726": {"price": "2929101"}, "727": {"price": "2928102"}, "728": {"price": "2928102"}, "729": {"price": "2928102"}, "730": {"price": "2928102"}, "731": {"price": "2928102"}, "732": {"price": "2927103"}, "733": {"price": "2928102"}, "734": {"price": "2928102"}, "735": {"price": "2927103"}, "736": {"price": "2927103"}, "737": {"price": "2927103"}, "738": {"price": "2926104"}, "739": {"price": "2925105"}, "740": {"price": "2926104"}, "741": {"price": "2925105"}, "742": {"price": "2925105"}, "743": {"price": "2925105"}, "744": {"price": "2921109"}, "745": {"price": "2920110"}, "746": {"price": "2920110"}, "747": {"price": "2919111"}, "748": {"price": "2918112"}, "749": {"price": "2917113"}, "750": {"price": "2919111"}, "751": {"price": "2919111"}, "752": {"price": "2919111"}, "753": {"price": "2919111"}, "754": {"price": "2919111"}, "755": {"price": "2919111"}, "756": {"price": "2919111"}, "757": {"price": "2919111"}, "758": {"price": "2919111"}, "759": {"price": "2919111"}, "760": {"price": "2919111"}, "761": {"price": "2919111"}, "762": {"price": "2919111"}, "763": {"price": "2919111"}, "764": {"price": "2919111"}, "765": {"price": "2919111"}, "766": {"price": "2919111"}, "767": {"price": "2919111"}, "768": {"price": "2919111"}, "769": {"price": "2919111"}, "770": {"price": "2919111"}, "771": {"price": "2919111"}, "772": {"price": "2919111"}, "773": {"price": "2919111"}, "774": {"price": "2919111"}, "775": {"price": "2919111"}, "776": {"price": "2919111"}, "777": {"price": "2919111"}, "778": {"price": "2919111"}, "779": {"price": "2919111"}, "780": {"price": "2919111"}, "781": {"price": "2919111"}, "782": {"price": "2919111"}, "783": {"price": "2919111"}, "784": {"price": "2919111"}, "785": {"price": "2919111"}, "786": {"price": "2919111"}, "787": {"price": "2919111"}, "788": {"price": "2919111"}, "789": {"price": "2919111"}, "790": {"price": "2919111"}, "791": {"price": "2919111"}, "792": {"price": "2919111"}, "793": {"price": "2919111"}, "794": {"price": "2919111"}, "795": {"price": "2919111"}, "796": {"price": "2919111"}, "797": {"price": "2919111"}, "798": {"price": "2919111"}, "799": {"price": "2919111"}, "800": {"price": "2919111"}, "801": {"price": "2919111"}, "802": {"price": "2919111"}, "803": {"price": "2919111"}, "804": {"price": "2919111"}, "805": {"price": "2919111"}, "806": {"price": "2919111"}, "807": {"price": "2919111"}, "808": {"price": "2919111"}, "809": {"price": "2919111"}, "810": {"price": "2919111"}, "811": {"price": "2919111"}, "812": {"price": "2919111"}, "813": {"price": "2919111"}, "814": {"price": "2919111"}, "815": {"price": "2919111"}, "816": {"price": "2919111"}, "817": {"price": "2919111"}, "818": {"price": "2919111"}, "819": {"price": "2919111"}, "820": {"price": "2919111"}, "821": {"price": "2919111"}, "822": {"price": "2919111"}, "823": {"price": "2919111"}, "824": {"price": "2919111"}, "825": {"price": "2919111"}, "826": {"price": "2919111"}, "827": {"price": "2919111"}, "828": {"price": "2919111"}, "829": {"price": "2919111"}, "830": {"price": "2919111"}, "831": {"price": "2919111"}, "832": {"price": "2919111"}, "833": {"price": "2919111"}, "834": {"price": "2919111"}, "835": {"price": "2919111"}, "836": {"price": "2919111"}, "837": {"price": "2919111"}, "838": {"price": "2919111"}, "839": {"price": "2919111"}, "840": {"price": "2919111"}, "841": {"price": "2919111"}, "842": {"price": "2919111"}, "843": {"price": "2919111"}, "844": {"price": "2919111"}, "845": {"price": "2919111"}, "846": {"price": "2919111"}, "847": {"price": "2919111"}, "848": {"price": "2919111"}, "849": {"price": "2919111"}, "850": {"price": "2919111"}, "851": {"price": "2919111"}, "852": {"price": "2919111"}, "853": {"price": "2919111"}, "854": {"price": "2919111"}, "855": {"price": "2919111"}, "856": {"price": "2919111"}, "857": {"price": "2919111"}, "858": {"price": "2919111"}, "859": {"price": "2919111"}, "860": {"price": "2919111"}, "861": {"price": "2919111"}}